{
  "name": "ParentGenre",
  "options": {
    "idInjection": false,
    "mysql": {
      "schema": "festival_master",
      "table": "genre_parents"
    },
    "relations": {}
  },
  "mixins": {
    "DeleteOverride": true
  },
  "properties": {
    "id": {
      "type": "Number",
      "id": 1,
      "required": true,
      "length": null,
      "precision": 10,
      "scale": 0,
      "mysql": {
        "columnName": "id",
        "dataType": "int",
        "dataLength": null,
        "dataPrecision": 10,
        "dataScale": 0,
        "nullable": "N"
      }
    },
    "genre": {
      "type": "Number",
      "required": true,
      "length": null,
      "precision": 10,
      "scale": 0,
      "mysql": {
        "columnName": "genre",
        "dataType": "int",
        "dataLength": null,
        "dataPrecision": 10,
        "dataScale": 0,
        "nullable": "N"
      }
    },
    "deleted": {
      "type": "Number",
      "required": true,
      "length": null,
      "precision": 10,
      "scale": 0,
      "mysql": {
        "columnName": "deleted",
        "dataType": "int",
        "dataLength": null,
        "dataPrecision": 10,
        "dataScale": 0,
        "nullable": "N"
      }
    },
    "timestamp": {
      "type": "Date",
      "required": true,
      "length": null,
      "precision": null,
      "scale": null,
      "mysql": {
        "columnName": "timestamp",
        "dataType": "timestamp",
        "dataLength": null,
        "dataPrecision": null,
        "dataScale": null,
        "nullable": "N"
      }
    }
  },
  "validations": [],
  "relations": {},
  "acls": [],
  "methods": {}
}
